README.md
setup.py
TOPSIS_Abhiroop_101803109.egg-info/PKG-INFO
TOPSIS_Abhiroop_101803109.egg-info/SOURCES.txt
TOPSIS_Abhiroop_101803109.egg-info/dependency_links.txt
TOPSIS_Abhiroop_101803109.egg-info/entry_points.txt
TOPSIS_Abhiroop_101803109.egg-info/requires.txt
TOPSIS_Abhiroop_101803109.egg-info/top_level.txt
src/topsis.py